linear2008/Linear.py
linear2008/__init__.py
linear2008-0.0.4.dist-info/METADATA
linear2008-0.0.4.dist-info/WHEEL
linear2008-0.0.4.dist-info/RECORD
