Metadata-Version: 2.3
Name: linear2008
Version: 0.0.4
Summary: Linear is your Python-powered Swiss Army knife for coding contests! Designed with ❤️ for competitive programmers, it streamlines your workflow by providing quick access to AtCoder/Codeforces resources, generating code templates, and visualizing rating progress - all from your terminal!
Author: LinusShyu
Author-email: awmtft@163.com
Requires-Python: >=3.12
Classifier: Programming Language :: Python :: 3
Classifier: Programming Language :: Python :: 3.12
Classifier: Programming Language :: Python :: 3.13
Requires-Dist: qrcode (>=7.4.2)
Requires-Dist: requests (>=2.32.3)
